{
    "questions": [
        {
            "id": 1,
            "title": "Узнавать об открытиях в области физики и математики.",
            "key": 1,
            "variants": [{ "title": "Да" }, { "title": "?" }, { "title": "Нет" }]
        },
        {
            "id": 2,
            "title": "Смотреть передачи о жизни растений и животных.",
            "key": 2,
            "variants": [{ "title": "Да" }, { "title": "?" }, { "title": "Нет" }]
        },
        {
            "id": 3,
            "title": "Выяснять устройство электроприборов.",
            "key": 3,
            "variants": [{ "title": "Да" }, { "title": "?" }, { "title": "Нет" }]
        },
        {
            "id": 4,
            "title": "Читать научно-популярные технические журналы.",
            "key": 4,
            "variants": [{ "title": "Да" }, { "title": "?" }, { "title": "Нет" }]
        },
        {
            "id": 5,
            "title": "Смотреть передачи о жизни людей в разных странах.",
            "key": 5,
            "variants": [{ "title": "Да" }, { "title": "?" }, { "title": "Нет" }]
        },
        {
            "id": 6,
            "title": "Бывать на выставках, концертах, спектаклях.",
            "key": 6,
            "variants": [{ "title": "Да" }, { "title": "?" }, { "title": "Нет" }]
        },
        {
            "id": 7,
            "title": "Обсуждать и анализировать события в стране и за рубежом.",
            "key": 7,
            "variants": [{ "title": "Да" }, { "title": "?" }, { "title": "Нет" }]
        },
        {
            "id": 8,
            "title": "Наблюдать за работой медсестры, врача.",
            "key": 8,
            "variants": [{ "title": "Да" }, { "title": "?" }, { "title": "Нет" }]
        },
        {
            "id": 9,
            "title": "Создавать уют и порядок в доме, классе, школе.",
            "key": 9,
            "variants": [{ "title": "Да" }, { "title": "?" }, { "title": "Нет" }]
        },
        {
            "id": 10,
            "title": "Читать книги и смотреть фильмы о войнах и сражениях.",
            "key": 10,
            "variants": [{ "title": "Да" }, { "title": "?" }, { "title": "Нет" }]
        },
        {
            "id": 11,
            "title": "Заниматься математическими расчетами и вычислениями.",
            "key": 1,
            "variants": [{ "title": "Да" }, { "title": "?" }, { "title": "Нет" }]
        },
        {
            "id": 12,
            "title": "Узнавать об открытиях в области химии и биологии.",
            "key": 2,
            "variants": [{ "title": "Да" }, { "title": "?" }, { "title": "Нет" }]
        },
        {
            "id": 13,
            "title": "Ремонтировать бытовые электроприборы.",
            "key": 3,
            "variants": [{ "title": "Да" }, { "title": "?" }, { "title": "Нет" }]
        },
        {
            "id": 14,
            "title": "Посещать технические выставки, знакомиться с достижениями науки и техники.",
            "key": 4,
            "variants": [{ "title": "Да" }, { "title": "?" }, { "title": "Нет" }]
        },
        {
            "id": 15,
            "title": "Ходить в походы, бывать в новых неизведанных местах.",
            "key": 5,
            "variants": [{ "title": "Да" }, { "title": "?" }, { "title": "Нет" }]
        },
        {
            "id": 16,
            "title": "Читать отзывы и статьи о книгах, фильмах, концертах.",
            "key": 6,
            "variants": [{ "title": "Да" }, { "title": "?" }, { "title": "Нет" }]
        },
        {
            "id": 17,
            "title": "Участвовать в общественной жизни школы, города.",
            "key": 7,
            "variants": [{ "title": "Да" }, { "title": "?" }, { "title": "Нет" }]
        },
        {
            "id": 18,
            "title": "Объяснять одноклассникам учебный материал.",
            "key": 8,
            "variants": [{ "title": "Да" }, { "title": "?" }, { "title": "Нет" }]
        },
        {
            "id": 19,
            "title": "Самостоятельно выполнять работу по хозяйству.",
            "key": 9,
            "variants": [{ "title": "Да" }, { "title": "?" }, { "title": "Нет" }]
        },
        {
            "id": 20,
            "title": "Соблюдать режим, вести здоровый образ жизни.",
            "key": 10,
            "variants": [{ "title": "Да" }, { "title": "?" }, { "title": "Нет" }]
        },
        {
            "id": 21,
            "title": "Проводить опыты по физике.",
            "key": 1,
            "variants": [{ "title": "Да" }, { "title": "?" }, { "title": "Нет" }]
        },
        {
            "id": 22,
            "title": "Ухаживать за животными, растениями.",
            "key": 2,
            "variants": [{ "title": "Да" }, { "title": "?" }, { "title": "Нет" }]
        },
        {
            "id": 23,
            "title": "Читать статьи об электронике и радиотехнике.",
            "key": 3,
            "variants": [{ "title": "Да" }, { "title": "?" }, { "title": "Нет" }]
        },
        {
            "id": 24,
            "title": "Собирать и ремонтировать часы, замки, велосипеды.",
            "key": 4,
            "variants": [{ "title": "Да" }, { "title": "?" }, { "title": "Нет" }]
        },
        {
            "id": 25,
            "title": "Коллекционировать камни, минералы.",
            "key": 5,
            "variants": [{ "title": "Да" }, { "title": "?" }, { "title": "Нет" }]
        },
        {
            "id": 26,
            "title": "Вести дневник, сочинять стихи и рассказы.",
            "key": 6,
            "variants": [{ "title": "Да" }, { "title": "?" }, { "title": "Нет" }]
        },
        {
            "id": 27,
            "title": "Читать биографии известных политиков, книги по истории.",
            "key": 7,
            "variants": [{ "title": "Да" }, { "title": "?" }, { "title": "Нет" }]
        },
        {
            "id": 28,
            "title": "Играть с детьми, помогать делать уроки младшим.",
            "key": 8,
            "variants": [{ "title": "Да" }, { "title": "?" }, { "title": "Нет" }]
        },
        {
            "id": 29,
            "title": "Закупать продукты для дома, вести учет расходов.",
            "key": 9,
            "variants": [{ "title": "Да" }, { "title": "?" }, { "title": "Нет" }]
        },
        {
            "id": 30,
            "title": "Участвовать в военных играх, походах.",
            "key": 10,
            "variants": [{ "title": "Да" }, { "title": "?" }, { "title": "Нет" }]
        },
        {
            "id": 31,
            "title": "Заниматься физикой и математикой сверх школьной программы.",
            "key": 1,
            "variants": [{ "title": "Да" }, { "title": "?" }, { "title": "Нет" }]
        },
        {
            "id": 32,
            "title": "Замечать и объяснять природные явления.",
            "key": 2,
            "variants": [{ "title": "Да" }, { "title": "?" }, { "title": "Нет" }]
        },
        {
            "id": 33,
            "title": "Собирать и ремонтировать компьютеры.",
            "key": 3,
            "variants": [{ "title": "Да" }, { "title": "?" }, { "title": "Нет" }]
        },
        {
            "id": 34,
            "title": "Строить чертежи, схемы, графики, в том числе на компьютере.",
            "key": 4,
            "variants": [{ "title": "Да" }, { "title": "?" }, { "title": "Нет" }]
        },
        {
            "id": 35,
            "title": "Участвовать в географических, геологических экспедициях.",
            "key": 5,
            "variants": [{ "title": "Да" }, { "title": "?" }, { "title": "Нет" }]
        },
        {
            "id": 36,
            "title": "Рассказывать друзьям о прочитанных книгах, увиденных фильмах и спектаклях.",
            "key": 6,
            "variants": [{ "title": "Да" }, { "title": "?" }, { "title": "Нет" }]
        },
        {
            "id": 37,
            "title": "Следить за политической жизнью в стране и за рубежом.",
            "key": 7,
            "variants": [{ "title": "Да" }, { "title": "?" }, { "title": "Нет" }]
        },
        {
            "id": 38,
            "title": "Ухаживать за маленькими детьми или близкими, если они заболели.",
            "key": 8,
            "variants": [{ "title": "Да" }, { "title": "?" }, { "title": "Нет" }]
        },
        {
            "id": 39,
            "title": "Искать и находить способы зарабатывания денег.",
            "key": 9,
            "variants": [{ "title": "Да" }, { "title": "?" }, { "title": "Нет" }]
        },
        {
            "id": 40,
            "title": "Заниматься физической культурой и спортом.",
            "key": 10,
            "variants": [{ "title": "Да" }, { "title": "?" }, { "title": "Нет" }]
        },
        {
            "id": 41,
            "title": "Участвовать в физико-математических олимпиадах.",
            "key": 1,
            "variants": [{ "title": "Да" }, { "title": "?" }, { "title": "Нет" }]
        },
        {
            "id": 42,
            "title": "Выполнять лабораторные опыты по химии и биологии.",
            "key": 2,
            "variants": [{ "title": "Да" }, { "title": "?" }, { "title": "Нет" }]
        },
        {
            "id": 43,
            "title": "Разбираться в принципах работы электроприборов.",
            "key": 3,
            "variants": [{ "title": "Да" }, { "title": "?" }, { "title": "Нет" }]
        },
        {
            "id": 44,
            "title": "Разбираться в принципах работы различных механизмов.",
            "key": 4,
            "variants": [{ "title": "Да" }, { "title": "?" }, { "title": "Нет" }]
        },
        {
            "id": 45,
            "title": "“Читать” географические и геологические карты.",
            "key": 5,
            "variants": [{ "title": "Да" }, { "title": "?" }, { "title": "Нет" }]
        },
        {
            "id": 46,
            "title": "Участвовать в спектаклях, концертах.",
            "key": 6,
            "variants": [{ "title": "Да" }, { "title": "?" }, { "title": "Нет" }]
        },
        {
            "id": 47,
            "title": "Изучать политику и экономику других стран.",
            "key": 7,
            "variants": [{ "title": "Да" }, { "title": "?" }, { "title": "Нет" }]
        },
        {
            "id": 48,
            "title": "Изучать причины поведения людей, строение человеческого организма.",
            "key": 8,
            "variants": [{ "title": "Да" }, { "title": "?" }, { "title": "Нет" }]
        },
        {
            "id": 49,
            "title": "Вкладывать заработанные деньги в домашний бюджет.",
            "key": 9,
            "variants": [{ "title": "Да" }, { "title": "?" }, { "title": "Нет" }]
        },
        {
            "id": 50,
            "title": "Участвовать в спортивных соревнованиях.",
            "key": 10,
            "variants": [{ "title": "Да" }, { "title": "?" }, { "title": "Нет" }]
        }
    ],
    "keys": [
        { "key": 1, "name": "Профессия связана с Физика и математика" },
        { "key": 2, "name": "Профессия связана с Химия и биология" },
        { "key": 3, "name": "Профессия связана с Радиотехника и электроника" },
        { "key": 4, "name": "Профессия связана с Механика и конструирование" },
        { "key": 5, "name": "Профессия связана с География и геология" },
        { "key": 6, "name": "Профессия связана с Литература и искусство" },
        { "key": 7, "name": "Профессия связана с История и политика" },
        { "key": 8, "name": "Профессия связана с Педагогика и медицина" },
        { "key": 9, "name": "Профессия связана с Предпринимательство и домоводство" },
        { "key": 10, "name": "Профессия связана с Спорт и военное дело" }
    ]
}